basicplot-0.1.0.dist-info/METADATA
basicplot-0.1.0.dist-info/WHEEL
basicplot.py
basicplot-0.1.0.dist-info/RECORD
